AUTHORS.rst
CONTRIBUTING.rst
HISTORY.md
LICENSE
MANIFEST.in
README.md
setup.cfg
setup.py
django_express_gateway.egg-info/PKG-INFO
django_express_gateway.egg-info/SOURCES.txt
django_express_gateway.egg-info/dependency_links.txt
django_express_gateway.egg-info/not-zip-safe
django_express_gateway.egg-info/requires.txt
django_express_gateway.egg-info/top_level.txt
express_gateway/__init__.py
express_gateway/admins.py
express_gateway/apps.py
express_gateway/authentications.py
express_gateway/models.py
express_gateway/services.py
tests/__init__.py
tests/conftest.py
tests/test_authentication.py