Metadata-Version: 1.1
Name: django-express-gateway
Version: 0.0.3
Summary: Integrating Django with Express Gateway
Home-page: https://github.com/NorakGithub/django_express_gateway
Author: Khemanorak Khath
Author-email: khath.khemanorak@gmail.com
License: MIT license
Keywords: django,express,gateway,express_gateway
Platform: UNKNOWN
Classifier: Development Status :: 2 - Pre-Alpha
Classifier: Intended Audience :: Developers
Classifier: License :: OSI Approved :: MIT License
Classifier: Natural Language :: English
Classifier: Programming Language :: Python :: 3
Classifier: Programming Language :: Python :: 3.4
Classifier: Programming Language :: Python :: 3.5
Classifier: Programming Language :: Python :: 3.6
Classifier: Programming Language :: Python :: 3.7
